Workbook

Sheet Parámetros
A1: LOGÍSTICA TOPS — Parámetros de cálculo
A3: Tarifa ANMAT ($/m²/mes, neto) | B3: 80000
A4: Tarifa Cargas Generales ($/m²/mes, neto) | B4: 20000
A5: IVA | B5: 0.21
A6: Moneda | B6: ARS
A7: Período | B7: Junio 2026
A9: Nota: las hojas de Detalle calculan con estas celdas (editá B3/B5 y recalculá).
A10: Fuente m²: planilla 'CLIENTES DE ANMAT Agustín Magaldi 1765/Osvaldo Cruz 3201' (Cynthia Alba, Drive, 18/06/2026).

Sheet Detalle clientes
A1: # | B1: Cliente | C1: Depósito | D1: Categoría | E1: m² ocupados | F1: $/m² (neto) | G1: Facturación mensual (neto) | H1: IVA (21%) | I1: Total c/IVA | J1: Observaciones
A2: 1 | B2: Royal Packs S.A. | C2: PB6 | D2: Almacenaje ANMAT | E2: 400 | F2: =Parámetros!$B$3 -> 80000 | G2: =E2*F2 -> 32000000 | H2: =G2*Parámetros!$B$5 -> 6720000 | I2: =G2+H2 -> 38720000 | J2: Mayor ocupante (31% del m2 ANMAT). Seguimiento de pago (ref. correos).
A3: 2 | B3: Silvia Noemí Willging | C3: PB7 | D3: Almacenaje ANMAT | E3: 70 | F3: =Parámetros!$B$3 -> 80000 | G3: =E3*F3 -> 5600000 | H3: =G3*Parámetros!$B$5 -> 1176000 | I3: =G3+H3 -> 6776000
A4: 3 | B4: DEO Distribuidores de Equipos Odontológicos S.R.L. | C4: PB8 | D4: Almacenaje ANMAT | E4: 50 | F4: =Parámetros!$B$3 -> 80000 | G4: =E4*F4 -> 4000000 | H4: =G4*Parámetros!$B$5 -> 840000 | I4: =G4+H4 -> 4840000
A5: 4 | B5: Medimpo S.R.L. | C5: PB9 | D5: Almacenaje ANMAT | E5: 50 | F5: =Parámetros!$B$3 -> 80000 | G5: =E5*F5 -> 4000000 | H5: =G5*Parámetros!$B$5 -> 840000 | I5: =G5+H5 -> 4840000
A6: 5 | B6: Técnicas Mínimo Invasivas S.A. | C6: PB10 | D6: Almacenaje ANMAT | E6: 50 | F6: =Parámetros!$B$3 -> 80000 | G6: =E6*F6 -> 4000000 | H6: =G6*Parámetros!$B$5 -> 840000 | I6: =G6+H6 -> 4840000
A7: 6 | B7: Compañía de Higiene S.R.L. | C7: PB11 | D7: Almacenaje ANMAT | E7: 50 | F7: =Parámetros!$B$3 -> 80000 | G7: =E7*F7 -> 4000000 | H7: =G7*Parámetros!$B$5 -> 840000 | I7: =G7+H7 -> 4840000
A8: 7 | B8: Lion Business | C8: PB12 | D8: Almacenaje ANMAT | E8: 70 | F8: =Parámetros!$B$3 -> 80000 | G8: =E8*F8 -> 5600000 | H8: =G8*Parámetros!$B$5 -> 1176000 | I8: =G8+H8 -> 6776000 | J8: Pago por adelantado (fe de errata clientes pendientes).
A9: 8 | B9: Korean Skin SRL | C9: PB14 | D9: Almacenaje ANMAT | E9: 15 | F9: =Parámetros!$B$3 -> 80000 | G9: =E9*F9 -> 1200000 | H9: =G9*Parámetros!$B$5 -> 252000 | I9: =G9+H9 -> 1452000
A10: 9 | B10: Padeco S.A. | C10: PB15 | D10: Almacenaje ANMAT | E10: 17 | F10: =Parámetros!$B$3 -> 80000 | G10: =E10*F10 -> 1360000 | H10: =G10*Parámetros!$B$5 -> 285600 | I10: =G10+H10 -> 1645600
A11: 10 | B11: Robi Insumos Médicos SRL | C11: PB16 | D11: Almacenaje ANMAT | E11: 17 | F11: =Parámetros!$B$3 -> 80000 | G11: =E11*F11 -> 1360000 | H11: =G11*Parámetros!$B$5 -> 285600 | I11: =G11+H11 -> 1645600
A12: 11 | B12: Migliore SRL | C12: PB17 | D12: Almacenaje ANMAT | E12: 25 | F12: =Parámetros!$B$3 -> 80000 | G12: =E12*F12 -> 2000000 | H12: =G12*Parámetros!$B$5 -> 420000 | I12: =G12+H12 -> 2420000
A13: 12 | B13: Medical Inputs S.R.L. | C13: PB18 | D13: Almacenaje ANMAT | E13: 30 | F13: =Parámetros!$B$3 -> 80000 | G13: =E13*F13 -> 2400000 | H13: =G13*Parámetros!$B$5 -> 504000 | I13: =G13+H13 -> 2904000
A14: 13 | B14: Dana Yasmín Atena | C14: PB19 | D14: Almacenaje ANMAT | E14: 17 | F14: =Parámetros!$B$3 -> 80000 | G14: =E14*F14 -> 1360000 | H14: =G14*Parámetros!$B$5 -> 285600 | I14: =G14+H14 -> 1645600
A15: 14 | B15: Kodent S.A. | C15: PB20+PB21 | D15: Almacenaje ANMAT | E15: 37 | F15: =Parámetros!$B$3 -> 80000 | G15: =E15*F15 -> 2960000 | H15: =G15*Parámetros!$B$5 -> 621600 | I15: =G15+H15 -> 3581600 | J15: Ocupa 2 depósitos (20+17 m2); consolidado como un cliente.
A16: 15 | B16: Amaoto S.R.L. | C16: PB22 | D16: Almacenaje ANMAT | E16: 17 | F16: =Parámetros!$B$3 -> 80000 | G16: =E16*F16 -> 1360000 | H16: =G16*Parámetros!$B$5 -> 285600 | I16: =G16+H16 -> 1645600
A17: 16 | B17: Business for Pharma SRL | C17: PB23 | D17: Almacenaje ANMAT | E17: 35 | F17: =Parámetros!$B$3 -> 80000 | G17: =E17*F17 -> 2800000 | H17: =G17*Parámetros!$B$5 -> 588000 | I17: =G17+H17 -> 3388000 | J17: Factura junio real informada por Ruth: $553.275 (≈ $15.808/m2).
A18: 17 | B18: Tinu SRL | C18: PB24 | D18: Almacenaje ANMAT | E18: 17 | F18: =Parámetros!$B$3 -> 80000 | G18: =E18*F18 -> 1360000 | H18: =G18*Parámetros!$B$5 -> 285600 | I18: =G18+H18 -> 1645600
A19: 18 | B19: Peghi Commerce S.A.S. | C19: PB25 | D19: Almacenaje ANMAT | E19: 17 | F19: =Parámetros!$B$3 -> 80000 | G19: =E19*F19 -> 1360000 | H19: =G19*Parámetros!$B$5 -> 285600 | I19: =G19+H19 -> 1645600 | J19: Consulta de pago junio enviada (seguimiento).
A20: 19 | B20: Bio Analítica S.A. | C20: PB26 | D20: Almacenaje ANMAT | E20: 50 | F20: =Parámetros!$B$3 -> 80000 | G20: =E20*F20 -> 4000000 | H20: =G20*Parámetros!$B$5 -> 840000 | I20: =G20+H20 -> 4840000
A21: 20 | B21: Wintrade S.A. | C21: PB27 | D21: Almacenaje ANMAT | E21: 70 | F21: =Parámetros!$B$3 -> 80000 | G21: =E21*F21 -> 5600000 | H21: =G21*Parámetros!$B$5 -> 1176000 | I21: =G21+H21 -> 6776000
A22: 21 | B22: Forever Living Products Argentina SRL | C22: PB28 | D22: Almacenaje ANMAT | E22: 35 | F22: =Parámetros!$B$3 -> 80000 | G22: =E22*F22 -> 2800000 | H22: =G22*Parámetros!$B$5 -> 588000 | I22: =G22+H22 -> 3388000 | J22: PB28/29 (70 m2) dividido 35+35 con Panalab.
A23: 22 | B23: Panalab S.A. | C23: PB29 | D23: Almacenaje ANMAT | E23: 35 | F23: =Parámetros!$B$3 -> 80000 | G23: =E23*F23 -> 2800000 | H23: =G23*Parámetros!$B$5 -> 588000 | I23: =G23+H23 -> 3388000 | J23: PB28/29 (70 m2) dividido 35+35 con Forever Living.
A24: 23 | B24: Rol Latino Medical SRL | C24: PB (s/n, junto al taller) | D24: Almacenaje ANMAT | E24: 38 | F24: =Parámetros!$B$3 -> 80000 | G24: =E24*F24 -> 3040000 | H24: =G24*Parámetros!$B$5 -> 638400 | I24: =G24+H24 -> 3678400 | J24: Agregado por Cynthia; no figuraba en el plano original.
A25: 24 | B25: Medicina del Plata SRL | C25: PB31 | D25: Almacenaje ANMAT | E25: 70 | F25: =Parámetros!$B$3 -> 80000 | G25: =E25*F25 -> 5600000 | H25: =G25*Parámetros!$B$5 -> 1176000 | I25: =G25+H25 -> 6776000
A26: 25 | B26: Ingemed S.A. | C26: PB32 | D26: Almacenaje ANMAT | E26: 10 | F26: =Parámetros!$B$3 -> 80000 | G26: =E26*F26 -> 800000 | H26: =G26*Parámetros!$B$5 -> 168000 | I26: =G26+H26 -> 968000
B27: TOTAL / PROMEDIO | E27: =SUM(E2:E26) -> 1292 | F27: =AVERAGE(F2:F26) -> 80000 | G27: =SUM(G2:G26) -> 103360000 | H27: =SUM(H2:H26) -> 21705600 | I27: =SUM(I2:I26) -> 125065600
B29: Espacios NO facturables (excluidos de la facturación):
B30: Recepción y Expedición (espacio interno) | C30: PB13 | E30: 30 | J30: No facturable (operación interna).
B31: LIBRE / Disponible | C31: PB30 | E31: 107 | J31: Vacante: lucro cesante. Oportunidad comercial.

Sheet Totales y KPIs
A1: Resumen ejecutivo — Facturación ANMAT (Junio 2026)
A3: Clientes activos (ANMAT) | B3: =COUNTA('Detalle clientes'!B2:B26) -> 25
A4: m² ocupados (facturables) | B4: ='Detalle clientes'!E27 -> 1292
A5: m² libres (PB30) | B5: 107
A6: m² internos no facturables (PB13) | B6: 30
A7: Facturación mensual (neto) | B7: ='Detalle clientes'!G27 -> 103360000
A8: IVA (21%) | B8: ='Detalle clientes'!H27 -> 21705600
A9: Facturación total c/IVA | B9: ='Detalle clientes'!I27 -> 125065600
A10: Ticket promedio por cliente (neto) | B10: ='Detalle clientes'!G27/'Totales y KPIs'!B3 -> 4134400
A11: Precio promedio por m² (neto) | B11: ='Detalle clientes'!G27/'Detalle clientes'!E27 -> 80000
A12: Ocupación ANMAT (ocupados / ocupados+libres) | B12: ='Detalle clientes'!E27/('Detalle clientes'!E27+B5) -> 0.9235168
A13: Lucro cesante por vacancia (neto) | B13: =B5*Parámetros!$B$3 -> 8560000

Sheet Rankings
A1: Rankings (Junio 2026)
A3: Ranking por superficie (m²)
A4: # | B4: Cliente | C4: m² | D4: Facturación neto
A5: 1 | B5: Royal Packs S.A. | C5: 400 | D5: =C5*Parámetros!$B$3 -> 32000000
A6: 2 | B6: Silvia Noemí Willging | C6: 70 | D6: =C6*Parámetros!$B$3 -> 5600000
A7: 3 | B7: Lion Business | C7: 70 | D7: =C7*Parámetros!$B$3 -> 5600000
A8: 4 | B8: Wintrade S.A. | C8: 70 | D8: =C8*Parámetros!$B$3 -> 5600000
A9: 5 | B9: Medicina del Plata SRL | C9: 70 | D9: =C9*Parámetros!$B$3 -> 5600000
A10: 6 | B10: DEO Distribuidores de Equipos Odontológicos S.R.L. | C10: 50 | D10: =C10*Parámetros!$B$3 -> 4000000
A11: 7 | B11: Medimpo S.R.L. | C11: 50 | D11: =C11*Parámetros!$B$3 -> 4000000
A12: 8 | B12: Técnicas Mínimo Invasivas S.A. | C12: 50 | D12: =C12*Parámetros!$B$3 -> 4000000
A13: 9 | B13: Compañía de Higiene S.R.L. | C13: 50 | D13: =C13*Parámetros!$B$3 -> 4000000
A14: 10 | B14: Bio Analítica S.A. | C14: 50 | D14: =C14*Parámetros!$B$3 -> 4000000
A15: 11 | B15: Rol Latino Medical SRL | C15: 38 | D15: =C15*Parámetros!$B$3 -> 3040000
A16: 12 | B16: Kodent S.A. | C16: 37 | D16: =C16*Parámetros!$B$3 -> 2960000
... A29: 25 | B29: Ingemed S.A. | C29: 10 | D29: =C29*Parámetros!$B$3 -> 800000
A31: Nota: con tarifa uniforme ($/m² constante), el ranking por facturación coincide con el de superficie,
A32: y el ranking por valor unitario ($/m²) es uniforme para todos los clientes ANMAT.
